numexpr_mod/cpuinfo.py
numexpr_mod/version.py
numexpr_mod/expressions.py
numexpr_mod/__init__.py
numexpr_mod/interpreter.cpython-38-darwin.so
numexpr_mod/utils.py
numexpr_mod/necompiler.py
numexpr_mod/tests/__init__.py
numexpr_mod/tests/test_numexpr.py
numexpr_mod-2.8.6.dist-info/RECORD
numexpr_mod-2.8.6.dist-info/WHEEL
numexpr_mod-2.8.6.dist-info/top_level.txt
numexpr_mod-2.8.6.dist-info/LICENSE.txt
numexpr_mod-2.8.6.dist-info/AUTHORS.txt
numexpr_mod-2.8.6.dist-info/METADATA
