Metadata-Version: 2.1
Name: numexpr-mod
Version: 2.8.6
Summary: Fast numerical expression evaluator for NumPy
Home-page: https://github.com/mrcheatak/numexpr_mod
Author: Alex K.
License: MIT
Classifier: Development Status :: 6 - Mature
Classifier: Intended Audience :: Financial and Insurance Industry
Classifier: Intended Audience :: Science/Research
Classifier: License :: OSI Approved :: MIT License
Classifier: Programming Language :: Python :: 3
Classifier: Programming Language :: Python :: 3.7
Classifier: Programming Language :: Python :: 3.8
Classifier: Programming Language :: Python :: 3.9
Classifier: Programming Language :: Python :: 3.10
Classifier: Programming Language :: Python :: 3.11
Classifier: Operating System :: Microsoft :: Windows
Classifier: Operating System :: POSIX
Classifier: Operating System :: MacOS
Requires-Python: >=3.7
License-File: LICENSE.txt
License-File: AUTHORS.txt
